<?xml version="1.0" encoding="utf-8" ?>
<?xml-stylesheet type='text/xsl' href='mesmer1.xsl'?>
<me:mesmer xmlns="http://www.xml-cml.org/schema" xmlns:me="http://www.chem.leeds.ac.uk/mesmer">
    <moleculeList>
        <molecule id="OH_acetylene_adduct">
            <atomarray>
                <atom id="a1" elementType="C" />
                <atom id="a2" elementType="C" />
                <atom id="a3" elementType="O" />
                <atom id="a4" elementType="H" />
                <atom id="a5" elementType="H" />
                <atom id="a6" elementType="H" />
            </atomarray>
            <bondarray>
                <bond atomRefs2="a1 a2" order="2" />
                <bond atomRefs2="a1 a3" order="1" />
                <bond atomRefs2="a3 a4" order="1" />
                <bond atomRefs2="a1 a5" order="1" />
                <bond atomRefs2="a2 a6" order="1" />
            </bondarray>
            <propertyList>
                <property dictRef="me:ZPE">
                    <scalar units="kcal/mol">0.0</scalar>
                </property>
                <property dictRef="me:rotConsts">
                    <array units="cm-1">0.32031 0.36452 2.64058</array>
                </property>
                <property dictRef="me:symmetryNumber">
                    <scalar>1</scalar>
                </property>
                <property dictRef="me:vibFreqs">
                    <array units="cm-1">464.0 474.0 567.0 770.0 848.0 1099.0 1244.0 1354.0 1667.0 3101.0 3300.0 3797.0</array>
                </property>
                <property dictRef="me:MW">
                    <scalar>43</scalar>
                </property>
                <property dictRef="me:epsilon">
                    <scalar>250.0</scalar>
                </property>
                <property dictRef="me:sigma">
                    <scalar>5.0</scalar>
                </property>
                <property dictRef="me:deltaEDown">
                    <scalar units="cm-1">250.0</scalar>
                </property>
                <property dictRef="me:spinMultiplicity">
                    <scalar>2</scalar>
                </property>
            </propertyList>
            <me:DOSCMethod>Classical rotors</me:DOSCMethod>
            <me:densityOfStatesList calculated="20080114_153204">
                <me:description>Partition function calculation at various temperatures.&#x0A; qtot : partition function as a product of quantum mechanical partition functions for vibrations (1-D harmonic oscillator) and classifical partition functions for rotations&#x0A; sumc : (user calculated) cell based partition function &#x0A; sumg : (user calculated) grain based partition function </me:description>
                <me:densityOfStates>
                    <me:T>200</me:T>
                    <me:qtot>5744.78</me:qtot>
                    <me:sumc>11490</me:sumc>
                    <me:sumg>11480.2</me:sumg>
                </me:densityOfStates>
                <me:densityOfStates>
                    <me:T>300</me:T>
                    <me:qtot>13547.2</me:qtot>
                    <me:sumc>27095</me:sumc>
                    <me:sumg>27084.6</me:sumg>
                </me:densityOfStates>
                <me:densityOfStates>
                    <me:T>400</me:T>
                    <me:qtot>29890.4</me:qtot>
                    <me:sumc>59781.7</me:sumc>
                    <me:sumg>59768.8</me:sumg>
                </me:densityOfStates>
                <me:densityOfStates>
                    <me:T>500</me:T>
                    <me:qtot>63729.1</me:qtot>
                    <me:sumc>127460</me:sumc>
                    <me:sumg>127442</me:sumg>
                </me:densityOfStates>
                <me:densityOfStates>
                    <me:T>600</me:T>
                    <me:qtot>131961</me:qtot>
                    <me:sumc>263925</me:sumc>
                    <me:sumg>263900</me:sumg>
                </me:densityOfStates>
                <me:densityOfStates>
                    <me:T>700</me:T>
                    <me:qtot>265512</me:qtot>
                    <me:sumc>531027</me:sumc>
                    <me:sumg>530990</me:sumg>
                </me:densityOfStates>
                <me:densityOfStates>
                    <me:T>800</me:T>
                    <me:qtot>519336</me:qtot>
                    <me:sumc>1.03868e+006</me:sumc>
                    <me:sumg>1.03862e+006</me:sumg>
                </me:densityOfStates>
                <me:densityOfStates>
                    <me:T>900</me:T>
                    <me:qtot>988504</me:qtot>
                    <me:sumc>1.97702e+006</me:sumc>
                    <me:sumg>1.97693e+006</me:sumg>
                </me:densityOfStates>
                <me:densityOfStates>
                    <me:T>1000</me:T>
                    <me:qtot>1.83349e+006</me:qtot>
                    <me:sumc>3.66699e+006</me:sumc>
                    <me:sumg>3.66686e+006</me:sumg>
                </me:densityOfStates>
                <me:densityOfStates>
                    <me:T>1100</me:T>
                    <me:qtot>3.3191e+006</me:qtot>
                    <me:sumc>6.63822e+006</me:sumc>
                    <me:sumg>6.63803e+006</me:sumg>
                </me:densityOfStates>
                <me:densityOfStates>
                    <me:T>1200</me:T>
                    <me:qtot>5.87336e+006</me:qtot>
                    <me:sumc>1.17467e+007</me:sumc>
                    <me:sumg>1.17465e+007</me:sumg>
                </me:densityOfStates>
                <me:densityOfStates>
                    <me:T>1300</me:T>
                    <me:qtot>1.01748e+007</me:qtot>
                    <me:sumc>2.03497e+007</me:sumc>
                    <me:sumg>2.03493e+007</me:sumg>
                </me:densityOfStates>
                <me:densityOfStates>
                    <me:T>1400</me:T>
                    <me:qtot>1.72801e+007</me:qtot>
                    <me:sumc>3.45603e+007</me:sumc>
                    <me:sumg>3.45597e+007</me:sumg>
                </me:densityOfStates>
                <me:densityOfStates>
                    <me:T>1500</me:T>
                    <me:qtot>2.88077e+007</me:qtot>
                    <me:sumc>5.76155e+007</me:sumc>
                    <me:sumg>5.76146e+007</me:sumg>
                </me:densityOfStates>
                <me:densityOfStates>
                    <me:T>1600</me:T>
                    <me:qtot>4.71978e+007</me:qtot>
                    <me:sumc>9.43957e+007</me:sumc>
                    <me:sumg>9.43944e+007</me:sumg>
                </me:densityOfStates>
                <me:densityOfStates>
                    <me:T>1700</me:T>
                    <me:qtot>7.60773e+007</me:qtot>
                    <me:sumc>1.52155e+008</me:sumc>
                    <me:sumg>1.52153e+008</me:sumg>
                </me:densityOfStates>
                <me:densityOfStates>
                    <me:T>1800</me:T>
                    <me:qtot>1.20764e+008</me:qtot>
                    <me:sumc>2.41529e+008</me:sumc>
                    <me:sumg>2.41526e+008</me:sumg>
                </me:densityOfStates>
                <me:densityOfStates>
                    <me:T>1900</me:T>
                    <me:qtot>1.88956e+008</me:qtot>
                    <me:sumc>3.77913e+008</me:sumc>
                    <me:sumg>3.77909e+008</me:sumg>
                </me:densityOfStates>
                <me:densityOfStates>
                    <me:T>2000</me:T>
                    <me:qtot>2.91665e+008</me:qtot>
                    <me:sumc>5.83331e+008</me:sumc>
                    <me:sumg>5.83326e+008</me:sumg>
                </me:densityOfStates>
                <me:densityOfStates>
                    <me:T>2100</me:T>
                    <me:qtot>4.44467e+008</me:qtot>
                    <me:sumc>8.88934e+008</me:sumc>
                    <me:sumg>8.88927e+008</me:sumg>
                </me:densityOfStates>
                <me:densityOfStates>
                    <me:T>2200</me:T>
                    <me:qtot>6.69159e+008</me:qtot>
                    <me:sumc>1.33832e+009</me:sumc>
                    <me:sumg>1.33831e+009</me:sumg>
                </me:densityOfStates>
                <me:densityOfStates>
                    <me:T>2300</me:T>
                    <me:qtot>9.95946e+008</me:qtot>
                    <me:sumc>1.99189e+009</me:sumc>
                    <me:sumg>1.99188e+009</me:sumg>
                </me:densityOfStates>
                <me:densityOfStates>
                    <me:T>2400</me:T>
                    <me:qtot>1.46629e+009</me:qtot>
                    <me:sumc>2.93256e+009</me:sumc>
                    <me:sumg>2.93254e+009</me:sumg>
                </me:densityOfStates>
                <me:densityOfStates>
                    <me:T>2500</me:T>
                    <me:qtot>2.13658e+009</me:qtot>
                    <me:sumc>4.27311e+009</me:sumc>
                    <me:sumg>4.27308e+009</me:sumg>
                </me:densityOfStates>
                <me:densityOfStates>
                    <me:T>2600</me:T>
                    <me:qtot>3.08291e+009</me:qtot>
                    <me:sumc>6.16562e+009</me:sumc>
                    <me:sumg>6.16559e+009</me:sumg>
                </me:densityOfStates>
                <me:densityOfStates>
                    <me:T>2700</me:T>
                    <me:qtot>4.40709e+009</me:qtot>
                    <me:sumc>8.81352e+009</me:sumc>
                    <me:sumg>8.81348e+009</me:sumg>
                </me:densityOfStates>
                <me:densityOfStates>
                    <me:T>2800</me:T>
                    <me:qtot>6.24431e+009</me:qtot>
                    <me:sumc>1.24867e+010</me:sumc>
                    <me:sumg>1.24867e+010</me:sumg>
                </me:densityOfStates>
                <me:densityOfStates>
                    <me:T>2900</me:T>
                    <me:qtot>8.77282e+009</me:qtot>
                    <me:sumc>1.75406e+010</me:sumc>
                    <me:sumg>1.75406e+010</me:sumg>
                </me:densityOfStates>
                <me:densityOfStates>
                    <me:T>3000</me:T>
                    <me:qtot>1.2226e+010</me:qtot>
                    <me:sumc>2.44395e+010</me:sumc>
                    <me:sumg>2.44394e+010</me:sumg>
                </me:densityOfStates>
            </me:densityOfStatesList>
        </molecule>
        <molecule id="TS_1a">
            <atomarray>
                <atom id="a1" elementType="C" />
                <atom id="a2" elementType="C" />
                <atom id="a3" elementType="H" />
                <atom id="a4" elementType="H" />
                <atom id="a5" elementType="O" />
                <atom id="a6" elementType="H" />
            </atomarray>
            <bondarray>
                <bond atomRefs2="a1 a2" order="3" />
                <bond atomRefs2="a1 a3" order="1" />
                <bond atomRefs2="a2 a4" order="1" />
                <bond atomRefs2="a5 a6" order="1" />
            </bondarray>
            <propertyList>
                <property dictRef="me:ZPE">
                    <scalar units="kcal/mol">137.2</scalar>
                </property>
                <property dictRef="me:rotConsts">
                    <array units="cm-1">0.33065 0.39313 2.06178</array>
                </property>
                <property dictRef="me:symmetryNumber">
                    <scalar>1.0</scalar>
                </property>
                <property dictRef="me:vibFreqs">
                    <array units="cm-1">332.0 807.0 903.0 1010.0 1098.0 1158.0 1306.0 1407.0 1988.0 3127.0 3167.0</array>
                </property>
                <property dictRef="me:MW">
                    <scalar>43</scalar>
                </property>
                <property dictRef="me:spinMultiplicity">
                    <scalar>2</scalar>
                </property>
            </propertyList>
            <me:DOSCMethod>Classical rotors</me:DOSCMethod>
        </molecule>
        <molecule id="OH">
            <atomarray>
                <atom id="a1" elementType="O" />
                <atom id="a2" elementType="H" />
            </atomarray>
            <bondarray>
                <bond atomRefs2="a1 a2" order="1" />
            </bondarray>
            <propertyList>
                <property dictRef="me:ZPE">
                    <scalar units="kcal/mol">0.0</scalar>
                </property>
                <property dictRef="me:rotConsts">
                    <array units="cm-1">19.2438</array>
                </property>
                <property dictRef="me:symmetryNumber">
                    <scalar>1</scalar>
                </property>
                <property dictRef="me:vibFreqs">
                    <array units="cm-1">3722.0</array>
                </property>
                <property dictRef="me:MW">
                    <scalar>17</scalar>
                </property>
                <property dictRef="me:spinMultiplicity">
                    <scalar>2</scalar>
                </property>
                <property dictRef="me:eletronicExcitation">
                    <array units="cm-1">139.7</array>
                </property>
            </propertyList>
            <me:DOSCMethod>Classical rotors</me:DOSCMethod>
            <me:densityOfStatesList calculated="20080114_153219">
                <me:description>Partition function calculation at various temperatures.&#x0A; qtot : partition function as a product of quantum mechanical partition functions for vibrations (1-D harmonic oscillator) and classifical partition functions for rotations&#x0A; sumc : (user calculated) cell based partition function &#x0A; sumg : (user calculated) grain based partition function </me:description>
                <me:densityOfStates>
                    <me:T>200</me:T>
                    <me:qtot>2675.03</me:qtot>
                    <me:sumc>19.8003</me:sumc>
                    <me:sumg>19.7832</me:sumg>
                </me:densityOfStates>
                <me:densityOfStates>
                    <me:T>300</me:T>
                    <me:qtot>4012.54</me:qtot>
                    <me:sumc>32.8502</me:sumc>
                    <me:sumg>32.8376</me:sumg>
                </me:densityOfStates>
                <me:densityOfStates>
                    <me:T>400</me:T>
                    <me:qtot>5350.06</me:qtot>
                    <me:sumc>46.4826</me:sumc>
                    <me:sumg>46.4726</me:sumg>
                </me:densityOfStates>
                <me:densityOfStates>
                    <me:T>500</me:T>
                    <me:qtot>6687.71</me:qtot>
                    <me:sumc>60.3992</me:sumc>
                    <me:sumg>60.3908</me:sumg>
                </me:densityOfStates>
                <me:densityOfStates>
                    <me:T>600</me:T>
                    <me:qtot>8026.14</me:qtot>
                    <me:sumc>74.4809</me:sumc>
                    <me:sumg>74.4738</me:sumg>
                </me:densityOfStates>
                <me:densityOfStates>
                    <me:T>700</me:T>
                    <me:qtot>9367.05</me:qtot>
                    <me:sumc>88.6832</me:sumc>
                    <me:sumg>88.677</me:sumg>
                </me:densityOfStates>
                <me:densityOfStates>
                    <me:T>800</me:T>
                    <me:qtot>10713.4</me:qtot>
                    <me:sumc>103.002</me:sumc>
                    <me:sumg>102.997</me:sumg>
                </me:densityOfStates>
                <me:densityOfStates>
                    <me:T>900</me:T>
                    <me:qtot>12069.1</me:qtot>
                    <me:sumc>117.458</me:sumc>
                    <me:sumg>117.453</me:sumg>
                </me:densityOfStates>
                <me:densityOfStates>
                    <me:T>1000</me:T>
                    <me:qtot>13438.6</me:qtot>
                    <me:sumc>132.085</me:sumc>
                    <me:sumg>132.081</me:sumg>
                </me:densityOfStates>
                <me:densityOfStates>
                    <me:T>1100</me:T>
                    <me:qtot>14826.6</me:qtot>
                    <me:sumc>146.923</me:sumc>
                    <me:sumg>146.919</me:sumg>
                </me:densityOfStates>
                <me:densityOfStates>
                    <me:T>1200</me:T>
                    <me:qtot>16237.4</me:qtot>
                    <me:sumc>162.013</me:sumc>
                    <me:sumg>162.009</me:sumg>
                </me:densityOfStates>
                <me:densityOfStates>
                    <me:T>1300</me:T>
                    <me:qtot>17675</me:qtot>
                    <me:sumc>177.393</me:sumc>
                    <me:sumg>177.39</me:sumg>
                </me:densityOfStates>
                <me:densityOfStates>
                    <me:T>1400</me:T>
                    <me:qtot>19142.8</me:qtot>
                    <me:sumc>193.098</me:sumc>
                    <me:sumg>193.095</me:sumg>
                </me:densityOfStates>
                <me:densityOfStates>
                    <me:T>1500</me:T>
                    <me:qtot>20643.9</me:qtot>
                    <me:sumc>209.159</me:sumc>
                    <me:sumg>209.156</me:sumg>
                </me:densityOfStates>
                <me:densityOfStates>
                    <me:T>1600</me:T>
                    <me:qtot>22180.8</me:qtot>
                    <me:sumc>225.602</me:sumc>
                    <me:sumg>225.599</me:sumg>
                </me:densityOfStates>
                <me:densityOfStates>
                    <me:T>1700</me:T>
                    <me:qtot>23755.6</me:qtot>
                    <me:sumc>242.451</me:sumc>
                    <me:sumg>242.448</me:sumg>
                </me:densityOfStates>
                <me:densityOfStates>
                    <me:T>1800</me:T>
                    <me:qtot>25370.2</me:qtot>
                    <me:sumc>259.723</me:sumc>
                    <me:sumg>259.72</me:sumg>
                </me:densityOfStates>
                <me:densityOfStates>
                    <me:T>1900</me:T>
                    <me:qtot>27026.1</me:qtot>
                    <me:sumc>277.436</me:sumc>
                    <me:sumg>277.433</me:sumg>
                </me:densityOfStates>
                <me:densityOfStates>
                    <me:T>2000</me:T>
                    <me:qtot>28724.5</me:qtot>
                    <me:sumc>295.603</me:sumc>
                    <me:sumg>295.6</me:sumg>
                </me:densityOfStates>
                <me:densityOfStates>
                    <me:T>2100</me:T>
                    <me:qtot>30466.5</me:qtot>
                    <me:sumc>314.235</me:sumc>
                    <me:sumg>314.233</me:sumg>
                </me:densityOfStates>
                <me:densityOfStates>
                    <me:T>2200</me:T>
                    <me:qtot>32253</me:qtot>
                    <me:sumc>333.344</me:sumc>
                    <me:sumg>333.342</me:sumg>
                </me:densityOfStates>
                <me:densityOfStates>
                    <me:T>2300</me:T>
                    <me:qtot>34084.7</me:qtot>
                    <me:sumc>352.936</me:sumc>
                    <me:sumg>352.934</me:sumg>
                </me:densityOfStates>
                <me:densityOfStates>
                    <me:T>2400</me:T>
                    <me:qtot>35962.2</me:qtot>
                    <me:sumc>373.02</me:sumc>
                    <me:sumg>373.018</me:sumg>
                </me:densityOfStates>
                <me:densityOfStates>
                    <me:T>2500</me:T>
                    <me:qtot>37886.2</me:qtot>
                    <me:sumc>393.6</me:sumc>
                    <me:sumg>393.598</me:sumg>
                </me:densityOfStates>
                <me:densityOfStates>
                    <me:T>2600</me:T>
                    <me:qtot>39857</me:qtot>
                    <me:sumc>414.683</me:sumc>
                    <me:sumg>414.681</me:sumg>
                </me:densityOfStates>
                <me:densityOfStates>
                    <me:T>2700</me:T>
                    <me:qtot>41875</me:qtot>
                    <me:sumc>436.273</me:sumc>
                    <me:sumg>436.271</me:sumg>
                </me:densityOfStates>
                <me:densityOfStates>
                    <me:T>2800</me:T>
                    <me:qtot>43940.6</me:qtot>
                    <me:sumc>458.373</me:sumc>
                    <me:sumg>458.371</me:sumg>
                </me:densityOfStates>
                <me:densityOfStates>
                    <me:T>2900</me:T>
                    <me:qtot>46054</me:qtot>
                    <me:sumc>480.986</me:sumc>
                    <me:sumg>480.984</me:sumg>
                </me:densityOfStates>
                <me:densityOfStates>
                    <me:T>3000</me:T>
                    <me:qtot>48215.5</me:qtot>
                    <me:sumc>504.116</me:sumc>
                    <me:sumg>504.114</me:sumg>
                </me:densityOfStates>
            </me:densityOfStatesList>
        </molecule>
        <molecule id="acetylene">
            <atomarray>
                <atom id="a1" elementType="C" />
                <atom id="a2" elementType="C" />
                <atom id="a3" elementType="H" />
                <atom id="a4" elementType="H" />
            </atomarray>
            <bondarray>
                <bond atomRefs2="a1 a2" order="3" />
                <bond atomRefs2="a1 a3" order="1" />
                <bond atomRefs2="a2 a4" order="1" />
            </bondarray>
            <propertyList>
                <property dictRef="me:ZPE">
                    <scalar units="kcal/mol">130.7</scalar>
                </property>
                <property dictRef="me:rotConsts">
                    <array units="cm-1">1.19205</array>
                </property>
                <property dictRef="me:symmetryNumber">
                    <scalar>2</scalar>
                </property>
                <property dictRef="me:vibFreqs">
                    <array units="cm-1">664.0 664.0 766.0 766.0 2066.0 3408.0 3509.0</array>
                </property>
                <property dictRef="me:MW">
                    <scalar>26</scalar>
                </property>
                <property dictRef="me:spinMultiplicity">
                    <scalar>1</scalar>
                </property>
            </propertyList>
            <me:DOSCMethod>Classical rotors</me:DOSCMethod>
            <me:densityOfStatesList calculated="20080114_153222">
                <me:description>Partition function calculation at various temperatures.&#x0A; qtot : partition function as a product of quantum mechanical partition functions for vibrations (1-D harmonic oscillator) and classifical partition functions for rotations&#x0A; sumc : (user calculated) cell based partition function &#x0A; sumg : (user calculated) grain based partition function </me:description>
                <me:densityOfStates>
                    <me:T>200</me:T>
                    <me:qtot>84.9511</me:qtot>
                    <me:sumc>59.7832</me:sumc>
                    <me:sumg>59.7318</me:sumg>
                </me:densityOfStates>
                <me:densityOfStates>
                    <me:T>300</me:T>
                    <me:qtot>142.387</me:qtot>
                    <me:sumc>100.203</me:sumc>
                    <me:sumg>100.165</me:sumg>
                </me:densityOfStates>
                <me:densityOfStates>
                    <me:T>400</me:T>
                    <me:qtot>229.235</me:qtot>
                    <me:sumc>161.321</me:sumc>
                    <me:sumg>161.287</me:sumg>
                </me:densityOfStates>
                <me:densityOfStates>
                    <me:T>500</me:T>
                    <me:qtot>361.469</me:qtot>
                    <me:sumc>254.379</me:sumc>
                    <me:sumg>254.344</me:sumg>
                </me:densityOfStates>
                <me:densityOfStates>
                    <me:T>600</me:T>
                    <me:qtot>558.534</me:qtot>
                    <me:sumc>393.061</me:sumc>
                    <me:sumg>393.024</me:sumg>
                </me:densityOfStates>
                <me:densityOfStates>
                    <me:T>700</me:T>
                    <me:qtot>845.539</me:qtot>
                    <me:sumc>595.038</me:sumc>
                    <me:sumg>594.996</me:sumg>
                </me:densityOfStates>
                <me:densityOfStates>
                    <me:T>800</me:T>
                    <me:qtot>1255.09</me:qtot>
                    <me:sumc>883.254</me:sumc>
                    <me:sumg>883.207</me:sumg>
                </me:densityOfStates>
                <me:densityOfStates>
                    <me:T>900</me:T>
                    <me:qtot>1829.24</me:qtot>
                    <me:sumc>1287.3</me:sumc>
                    <me:sumg>1287.25</me:sumg>
                </me:densityOfStates>
                <me:densityOfStates>
                    <me:T>1000</me:T>
                    <me:qtot>2621.71</me:qtot>
                    <me:sumc>1844.99</me:sumc>
                    <me:sumg>1844.93</me:sumg>
                </me:densityOfStates>
                <me:densityOfStates>
                    <me:T>1100</me:T>
                    <me:qtot>3700.47</me:qtot>
                    <me:sumc>2604.16</me:sumc>
                    <me:sumg>2604.09</me:sumg>
                </me:densityOfStates>
                <me:densityOfStates>
                    <me:T>1200</me:T>
                    <me:qtot>5150.71</me:qtot>
                    <me:sumc>3624.75</me:sumc>
                    <me:sumg>3624.66</me:sumg>
                </me:densityOfStates>
                <me:densityOfStates>
                    <me:T>1300</me:T>
                    <me:qtot>7078.21</me:qtot>
                    <me:sumc>4981.2</me:sumc>
                    <me:sumg>4981.1</me:sumg>
                </me:densityOfStates>
                <me:densityOfStates>
                    <me:T>1400</me:T>
                    <me:qtot>9613.25</me:qtot>
                    <me:sumc>6765.21</me:sumc>
                    <me:sumg>6765.09</me:sumg>
                </me:densityOfStates>
                <me:densityOfStates>
                    <me:T>1500</me:T>
                    <me:qtot>12915</me:qtot>
                    <me:sumc>9088.79</me:sumc>
                    <me:sumg>9088.65</me:sumg>
                </me:densityOfStates>
                <me:densityOfStates>
                    <me:T>1600</me:T>
                    <me:qtot>17176.6</me:qtot>
                    <me:sumc>12087.8</me:sumc>
                    <me:sumg>12087.7</me:sumg>
                </me:densityOfStates>
                <me:densityOfStates>
                    <me:T>1700</me:T>
                    <me:qtot>22630.6</me:qtot>
                    <me:sumc>15926</me:sumc>
                    <me:sumg>15925.8</me:sumg>
                </me:densityOfStates>
                <me:densityOfStates>
                    <me:T>1800</me:T>
                    <me:qtot>29555.3</me:qtot>
                    <me:sumc>20799.2</me:sumc>
                    <me:sumg>20799</me:sumg>
                </me:densityOfStates>
                <me:densityOfStates>
                    <me:T>1900</me:T>
                    <me:qtot>38282.2</me:qtot>
                    <me:sumc>26940.6</me:sumc>
                    <me:sumg>26940.4</me:sumg>
                </me:densityOfStates>
                <me:densityOfStates>
                    <me:T>2000</me:T>
                    <me:qtot>49203.1</me:qtot>
                    <me:sumc>34626.1</me:sumc>
                    <me:sumg>34625.8</me:sumg>
                </me:densityOfStates>
                <me:densityOfStates>
                    <me:T>2100</me:T>
                    <me:qtot>62779.3</me:qtot>
                    <me:sumc>44180.2</me:sumc>
                    <me:sumg>44179.9</me:sumg>
                </me:densityOfStates>
                <me:densityOfStates>
                    <me:T>2200</me:T>
                    <me:qtot>79551.2</me:qtot>
                    <me:sumc>55983.2</me:sumc>
                    <me:sumg>55982.8</me:sumg>
                </me:densityOfStates>
                <me:densityOfStates>
                    <me:T>2300</me:T>
                    <me:qtot>100148</me:qtot>
                    <me:sumc>70478.2</me:sumc>
                    <me:sumg>70477.8</me:sumg>
                </me:densityOfStates>
                <me:densityOfStates>
                    <me:T>2400</me:T>
                    <me:qtot>125302</me:qtot>
                    <me:sumc>88179.6</me:sumc>
                    <me:sumg>88179.1</me:sumg>
                </me:densityOfStates>
                <me:densityOfStates>
                    <me:T>2500</me:T>
                    <me:qtot>155856</me:qtot>
                    <me:sumc>109682</me:sumc>
                    <me:sumg>109681</me:sumg>
                </me:densityOfStates>
                <me:densityOfStates>
                    <me:T>2600</me:T>
                    <me:qtot>192783</me:qtot>
                    <me:sumc>135669</me:sumc>
                    <me:sumg>135668</me:sumg>
                </me:densityOfStates>
                <me:densityOfStates>
                    <me:T>2700</me:T>
                    <me:qtot>237198</me:qtot>
                    <me:sumc>166925</me:sumc>
                    <me:sumg>166924</me:sumg>
                </me:densityOfStates>
                <me:densityOfStates>
                    <me:T>2800</me:T>
                    <me:qtot>290374</me:qtot>
                    <me:sumc>204347</me:sumc>
                    <me:sumg>204347</me:sumg>
                </me:densityOfStates>
                <me:densityOfStates>
                    <me:T>2900</me:T>
                    <me:qtot>353764</me:qtot>
                    <me:sumc>248957</me:sumc>
                    <me:sumg>248956</me:sumg>
                </me:densityOfStates>
                <me:densityOfStates>
                    <me:T>3000</me:T>
                    <me:qtot>429013</me:qtot>
                    <me:sumc>301912</me:sumc>
                    <me:sumg>301911</me:sumg>
                </me:densityOfStates>
            </me:densityOfStatesList>
        </molecule>
        <molecule id="N_2">
            <atom elementType="N_2" />
            <propertyList>
                <property dictRef="me:epsilon">
                    <scalar>48.0</scalar>
                </property>
                <property dictRef="me:sigma">
                    <scalar>3.90</scalar>
                </property>
                <property dictRef="me:MW">
                    <scalar>28.0</scalar>
                </property>
            </propertyList>
        </molecule>
        <molecule id="source_0">
            <me:densityOfStatesList calculated="20080114_153227">
                <me:description>Partition function calculation at various temperatures.&#x0A; qtot : partition function as a product of quantum mechanical partition functions for vibrations (1-D harmonic oscillator) and classifical partition functions for rotations&#x0A; sumc : (user calculated) cell based partition function &#x0A; sumg : (user calculated) grain based partition function </me:description>
                <me:densityOfStates>
                    <me:T>200</me:T>
                    <me:qtot>0</me:qtot>
                    <me:sumc>1183.73</me:sumc>
                    <me:sumg>1182.72</me:sumg>
                </me:densityOfStates>
                <me:densityOfStates>
                    <me:T>300</me:T>
                    <me:qtot>0</me:qtot>
                    <me:sumc>3291.71</me:sumc>
                    <me:sumg>3290.45</me:sumg>
                </me:densityOfStates>
                <me:densityOfStates>
                    <me:T>400</me:T>
                    <me:qtot>0</me:qtot>
                    <me:sumc>7498.63</me:sumc>
                    <me:sumg>7497.02</me:sumg>
                </me:densityOfStates>
                <me:densityOfStates>
                    <me:T>500</me:T>
                    <me:qtot>0</me:qtot>
                    <me:sumc>15364.3</me:sumc>
                    <me:sumg>15362.2</me:sumg>
                </me:densityOfStates>
                <me:densityOfStates>
                    <me:T>600</me:T>
                    <me:qtot>0</me:qtot>
                    <me:sumc>29275.6</me:sumc>
                    <me:sumg>29272.8</me:sumg>
                </me:densityOfStates>
                <me:densityOfStates>
                    <me:T>700</me:T>
                    <me:qtot>0</me:qtot>
                    <me:sumc>52769.9</me:sumc>
                    <me:sumg>52766.2</me:sumg>
                </me:densityOfStates>
                <me:densityOfStates>
                    <me:T>800</me:T>
                    <me:qtot>0</me:qtot>
                    <me:sumc>90977.1</me:sumc>
                    <me:sumg>90972.2</me:sumg>
                </me:densityOfStates>
                <me:densityOfStates>
                    <me:T>900</me:T>
                    <me:qtot>0</me:qtot>
                    <me:sumc>151204</me:sumc>
                    <me:sumg>151198</me:sumg>
                </me:densityOfStates>
                <me:densityOfStates>
                    <me:T>1000</me:T>
                    <me:qtot>0</me:qtot>
                    <me:sumc>243697</me:sumc>
                    <me:sumg>243688</me:sumg>
                </me:densityOfStates>
                <me:densityOfStates>
                    <me:T>1100</me:T>
                    <me:qtot>0</me:qtot>
                    <me:sumc>382612</me:sumc>
                    <me:sumg>382601</me:sumg>
                </me:densityOfStates>
                <me:densityOfStates>
                    <me:T>1200</me:T>
                    <me:qtot>0</me:qtot>
                    <me:sumc>587257</me:sumc>
                    <me:sumg>587243</me:sumg>
                </me:densityOfStates>
                <me:densityOfStates>
                    <me:T>1300</me:T>
                    <me:qtot>0</me:qtot>
                    <me:sumc>883632</me:sumc>
                    <me:sumg>883614</me:sumg>
                </me:densityOfStates>
                <me:densityOfStates>
                    <me:T>1400</me:T>
                    <me:qtot>0</me:qtot>
                    <me:sumc>1.30635e+006</me:sumc>
                    <me:sumg>1.30633e+006</me:sumg>
                </me:densityOfStates>
                <me:densityOfStates>
                    <me:T>1500</me:T>
                    <me:qtot>0</me:qtot>
                    <me:sumc>1.901e+006</me:sumc>
                    <me:sumg>1.90098e+006</me:sumg>
                </me:densityOfStates>
                <me:densityOfStates>
                    <me:T>1600</me:T>
                    <me:qtot>0</me:qtot>
                    <me:sumc>2.72704e+006</me:sumc>
                    <me:sumg>2.727e+006</me:sumg>
                </me:densityOfStates>
                <me:densityOfStates>
                    <me:T>1700</me:T>
                    <me:qtot>0</me:qtot>
                    <me:sumc>3.86126e+006</me:sumc>
                    <me:sumg>3.86122e+006</me:sumg>
                </me:densityOfStates>
                <me:densityOfStates>
                    <me:T>1800</me:T>
                    <me:qtot>0</me:qtot>
                    <me:sumc>5.40203e+006</me:sumc>
                    <me:sumg>5.40197e+006</me:sumg>
                </me:densityOfStates>
                <me:densityOfStates>
                    <me:T>1900</me:T>
                    <me:qtot>0</me:qtot>
                    <me:sumc>7.47429e+006</me:sumc>
                    <me:sumg>7.47422e+006</me:sumg>
                </me:densityOfStates>
                <me:densityOfStates>
                    <me:T>2000</me:T>
                    <me:qtot>0</me:qtot>
                    <me:sumc>1.02356e+007</me:sumc>
                    <me:sumg>1.02355e+007</me:sumg>
                </me:densityOfStates>
                <me:densityOfStates>
                    <me:T>2100</me:T>
                    <me:qtot>0</me:qtot>
                    <me:sumc>1.3883e+007</me:sumc>
                    <me:sumg>1.38829e+007</me:sumg>
                </me:densityOfStates>
                <me:densityOfStates>
                    <me:T>2200</me:T>
                    <me:qtot>0</me:qtot>
                    <me:sumc>1.86617e+007</me:sumc>
                    <me:sumg>1.86615e+007</me:sumg>
                </me:densityOfStates>
                <me:densityOfStates>
                    <me:T>2300</me:T>
                    <me:qtot>0</me:qtot>
                    <me:sumc>2.48743e+007</me:sumc>
                    <me:sumg>2.48742e+007</me:sumg>
                </me:densityOfStates>
                <me:densityOfStates>
                    <me:T>2400</me:T>
                    <me:qtot>0</me:qtot>
                    <me:sumc>3.28927e+007</me:sumc>
                    <me:sumg>3.28925e+007</me:sumg>
                </me:densityOfStates>
                <me:densityOfStates>
                    <me:T>2500</me:T>
                    <me:qtot>0</me:qtot>
                    <me:sumc>4.31707e+007</me:sumc>
                    <me:sumg>4.31705e+007</me:sumg>
                </me:densityOfStates>
                <me:densityOfStates>
                    <me:T>2600</me:T>
                    <me:qtot>0</me:qtot>
                    <me:sumc>5.62594e+007</me:sumc>
                    <me:sumg>5.62592e+007</me:sumg>
                </me:densityOfStates>
                <me:densityOfStates>
                    <me:T>2700</me:T>
                    <me:qtot>0</me:qtot>
                    <me:sumc>7.28247e+007</me:sumc>
                    <me:sumg>7.28243e+007</me:sumg>
                </me:densityOfStates>
                <me:densityOfStates>
                    <me:T>2800</me:T>
                    <me:qtot>0</me:qtot>
                    <me:sumc>9.36667e+007</me:sumc>
                    <me:sumg>9.36663e+007</me:sumg>
                </me:densityOfStates>
                <me:densityOfStates>
                    <me:T>2900</me:T>
                    <me:qtot>0</me:qtot>
                    <me:sumc>1.19743e+008</me:sumc>
                    <me:sumg>1.19743e+008</me:sumg>
                </me:densityOfStates>
                <me:densityOfStates>
                    <me:T>3000</me:T>
                    <me:qtot>0</me:qtot>
                    <me:sumc>1.52195e+008</me:sumc>
                    <me:sumg>1.52195e+008</me:sumg>
                </me:densityOfStates>
            </me:densityOfStatesList>
        </molecule>
    </moleculeList>
    <reactionList>
        <reaction id="R1">
            <reactant>
                <molecule ref="OH" me:type="reactant" />
            </reactant>
            <reactant>
                <molecule ref="acetylene" me:type="excessReactant" />
            </reactant>
            <product>
                <molecule ref="OH_acetylene_adduct" me:type="modelled" />
            </product>
            <me:transitionState>
                <molecule ref="TS_1a" me:type="transitionState" />
            </me:transitionState>
            <!--Use zero point energies instead-->
            <me:MCRCMethod>Mesmer ILT</me:MCRCMethod>
            <me:activationEnergy>5.375</me:activationEnergy>
            <me:preExponential>7.00e-12</me:preExponential>
            <me:excessReactantConc>1.00e17</me:excessReactantConc>
            <me:nInfinity>0.0</me:nInfinity>
            <me:microRateList calculated="20080114_154733">
                <me:description>Microcanonical rate coefficients</me:description>
                <me:microRate>
                    <me:T>200</me:T>
                    <me:val>3.69611e-023</me:val>
                </me:microRate>
                <me:microRate>
                    <me:T>300</me:T>
                    <me:val>5.59844e-011</me:val>
                </me:microRate>
                <me:microRate>
                    <me:T>400</me:T>
                    <me:val>7.44131e-005</me:val>
                </me:microRate>
                <me:microRate>
                    <me:T>500</me:T>
                    <me:val>0.357369</me:val>
                </me:microRate>
                <me:microRate>
                    <me:T>600</me:T>
                    <me:val>101.086</me:val>
                </me:microRate>
                <me:microRate>
                    <me:T>700</me:T>
                    <me:val>5616.15</me:val>
                </me:microRate>
                <me:microRate>
                    <me:T>800</me:T>
                    <me:val>112375</me:val>
                </me:microRate>
                <me:microRate>
                    <me:T>900</me:T>
                    <me:val>1.13645e+006</me:val>
                </me:microRate>
                <me:microRate>
                    <me:T>1000</me:T>
                    <me:val>7.12548e+006</me:val>
                </me:microRate>
                <me:microRate>
                    <me:T>1100</me:T>
                    <me:val>3.15601e+007</me:val>
                </me:microRate>
                <me:microRate>
                    <me:T>1200</me:T>
                    <me:val>1.07749e+008</me:val>
                </me:microRate>
                <me:microRate>
                    <me:T>1300</me:T>
                    <me:val>3.01247e+008</me:val>
                </me:microRate>
                <me:microRate>
                    <me:T>1400</me:T>
                    <me:val>7.20193e+008</me:val>
                </me:microRate>
                <me:microRate>
                    <me:T>1500</me:T>
                    <me:val>1.51975e+009</me:val>
                </me:microRate>
                <me:microRate>
                    <me:T>1600</me:T>
                    <me:val>2.89885e+009</me:val>
                </me:microRate>
                <me:microRate>
                    <me:T>1700</me:T>
                    <me:val>5.0898e+009</me:val>
                </me:microRate>
                <me:microRate>
                    <me:T>1800</me:T>
                    <me:val>8.34311e+009</me:val>
                </me:microRate>
                <me:microRate>
                    <me:T>1900</me:T>
                    <me:val>1.29104e+010</me:val>
                </me:microRate>
                <me:microRate>
                    <me:T>2000</me:T>
                    <me:val>1.90279e+010</me:val>
                </me:microRate>
                <me:microRate>
                    <me:T>2100</me:T>
                    <me:val>2.69028e+010</me:val>
                </me:microRate>
                <me:microRate>
                    <me:T>2200</me:T>
                    <me:val>3.67028e+010</me:val>
                </me:microRate>
                <me:microRate>
                    <me:T>2300</me:T>
                    <me:val>4.85498e+010</me:val>
                </me:microRate>
                <me:microRate>
                    <me:T>2400</me:T>
                    <me:val>6.25166e+010</me:val>
                </me:microRate>
                <me:microRate>
                    <me:T>2500</me:T>
                    <me:val>7.86269e+010</me:val>
                </me:microRate>
                <me:microRate>
                    <me:T>2600</me:T>
                    <me:val>9.68568e+010</me:val>
                </me:microRate>
                <me:microRate>
                    <me:T>2700</me:T>
                    <me:val>1.17138e+011</me:val>
                </me:microRate>
                <me:microRate>
                    <me:T>2800</me:T>
                    <me:val>1.39361e+011</me:val>
                </me:microRate>
                <me:microRate>
                    <me:T>2900</me:T>
                    <me:val>1.63381e+011</me:val>
                </me:microRate>
                <me:microRate>
                    <me:T>3000</me:T>
                    <me:val>1.89022e+011</me:val>
                </me:microRate>
            </me:microRateList>
        </reaction>
    </reactionList>
    <me:conditions>
        <me:bathGas>N_2</me:bathGas>
        <me:conc>1000</me:conc>
        <!--Three ways to input temperatures at which calcs are to be done-->
        <me:temperature units="K">298.0</me:temperature>
        <!--<me:temperature initial="100" increment="50" final="500" />-->
        <!--<me:temperature increment="200" final="3000">2200</me:temperature>-->
    </me:conditions>
    <me:modelParameters>
        <!--Specify grain size directly...-->
        <me:grainSize units="cm-1">20</me:grainSize>
        <!--...or by the total number of grains
        <me:numberOfGrains> 500 </me:numberOfGrains>-->
        <!--Specify increased energy range 
        <me:maxTemperature>6000</me:maxTemperature>-->
        <me:energyAboveTheTopWell>20.</me:energyAboveTheTopWell>
    </me:modelParameters>
    <me:control>
        <me:testMicroRates />
        <me:printGrainDOS />
        <!--<me:printCellDOS />-->
        <me:printCollisionOperatorColumnSums />
        <me:printCellkE />
        <me:eigenvalues>0</me:eigenvalues>
    </me:control>
    <metadataList>
        <metadata name="dc:creator" content="Mesmer v0.1" />
        <metadata name="dc:description" content="Calculation of the interaction between collisional energy transfer and chemical reaction for dissociation, isomerization and association processes" />
        <metadata name="dc:date" content="20080114_153204" />
        <metadata name="dc:contributor" content="unknown" />
    </metadataList>
</me:mesmer>
